setup.cfg
setup.py
bin/python-simple-swiftclient
python_simple_swiftclient/__init__.py
python_simple_swiftclient/helper.py
python_simple_swiftclient/main.py
python_simple_swiftclient/swiftclient.py
python_simple_swiftclient.egg-info/PKG-INFO
python_simple_swiftclient.egg-info/SOURCES.txt
python_simple_swiftclient.egg-info/dependency_links.txt
python_simple_swiftclient.egg-info/top_level.txt