Metadata-Version: 1.0
Name: python-simple-swiftclient
Version: 0.0.3
Summary: A simple Openstack Swift Client written in Python to manage swift objects using just python standard libraries.
Home-page: https://github.com/hcltech-ssw/python-simple-swiftclient
Author: HCLTech-SSW Team
Author-email: hcl_ss_oss@hcl.com
License: UNKNOWN
Platform: UNKNOWN
